Workbook
Name Clothes: subcategory!$C$2:$C$3
Name Electronics: subcategory!$C$6:$C$7
Name Furniture: subcategory!$C$10:$C$11
Name Kitchen: subcategory!$C$8:$C$9
Name PersonalCare: subcategory!$C$4:$C$5

Sheet category
A1: CATEGORY
A2: No. | B2: CATEGORY | C2: GST
A3: =ROW()-2 -> 1 | B3: Clothes | C3: 5
A4: =ROW()-2 -> 2 | B4: Electronics | C4: 12
A5: =ROW()-2 -> 3 | B5: PersonalCare | C5: 18
A6: =ROW()-2 -> 4 | B6: Kitchen | C6: 12
A7: =ROW()-2 -> 5 | B7: Furniture | C7: 28

Sheet purchase report
A1: PURCHASE REPORT
A2: No. | B2: CATEGORY | C2: ITEM_NAME | D2: QTY | E2: PRICE | F2: AMOUNT | G2: GST | H2: GST_AMOUNT | I2: TOTAL_AMOUNT | J2: DATE
A3: 1 | B3: Clothes | C3: Girls Shirts | D3: 100 | E3: 400 | F3: =E3*D3 -> 40000 | G3: =IFERROR(VLOOKUP(B3,category!$B$3:$C$7,2,FALSE),"") -> 5 | H3: =F3*G3% -> 2000 | I3: =H3+F3 -> 42000 | J3: 46114
A4: 2 | B4: PersonalCare | C4: Shampoo | D4: 200 | E4: 600 | F4: =E4*D4 -> 120000 | G4: =IFERROR(VLOOKUP(B4,category!$B$3:$C$7,2,FALSE),"") -> 18 | H4: =F4*G4% -> 21600 | I4: =H4+F4 -> 141600 | J4: 46115
A5: 3 | B5: Electronics | C5: TV | D5: 50 | E5: 32000 | F5: =E5*D5 -> 1600000 | G5: =IFERROR(VLOOKUP(B5,category!$B$3:$C$7,2,FALSE),"") -> 12 | H5: =F5*G5% -> 192000 | I5: =H5+F5 -> 1792000 | J5: 46116
A6: 4 | B6: Kitchen | C6: Cooker | D6: 70 | E6: 1500 | F6: =E6*D6 -> 105000 | G6: =IFERROR(VLOOKUP(B6,category!$B$3:$C$7,2,FALSE),"") -> 12 | H6: =F6*G6% -> 12600 | I6: =H6+F6 -> 117600 | J6: 46117
A7: 5 | B7: Clothes | C7: T-shirts | D7: 300 | E7: 700 | F7: =E7*D7 -> 210000 | G7: =IFERROR(VLOOKUP(B7,category!$B$3:$C$7,2,FALSE),"") -> 5 | H7: =F7*G7% -> 10500 | I7: =H7+F7 -> 220500 | J7: 46118
A8: 6 | B8: PersonalCare | C8: Sunscreen | D8: 250 | E8: 200 | F8: =E8*D8 -> 50000 | G8: =IFERROR(VLOOKUP(B8,category!$B$3:$C$7,2,FALSE),"") -> 18 | H8: =F8*G8% -> 9000 | I8: =H8+F8 -> 59000 | J8: 46119
A9: 7 | B9: Furniture | C9: Sofa | D9: 20 | E9: 35000 | F9: =E9*D9 -> 700000 | G9: =IFERROR(VLOOKUP(B9,category!$B$3:$C$7,2,FALSE),"") -> 28 | H9: =F9*G9% -> 196000 | I9: =H9+F9 -> 896000 | J9: 46120
A10: 8 | B10: Kitchen | C10: Mixer | D10: 60 | E10: 2000 | F10: =E10*D10 -> 120000 | G10: =IFERROR(VLOOKUP(B10,category!$B$3:$C$7,2,FALSE),"") -> 12 | H10: =F10*G10% -> 14400 | I10: =H10+F10 -> 134400 | J10: 46121
A11: 9 | B11: Furniture | C11: Bed | D11: 10 | E11: 75000 | F11: =E11*D11 -> 750000 | G11: =IFERROR(VLOOKUP(B11,category!$B$3:$C$7,2,FALSE),"") -> 28 | H11: =F11*G11% -> 210000 | I11: =H11+F11 -> 960000 | J11: 46122
A12: 10 | B12: Electronics | C12: AC | D12: 45 | E12: 25000 | F12: =E12*D12 -> 1125000 | G12: =IFERROR(VLOOKUP(B12,category!$B$3:$C$7,2,FALSE),"") -> 12 | H12: =F12*G12% -> 135000 | I12: =H12+F12 -> 1260000 | J12: 46123

Sheet sales report
A1: SALES REPORT
A2: No. | B2: CATEGORY | C2: ITEM_NAME | D2: SALE_QTY | E2: PRICE | F2: SALE_PRICE | G2: AMOUNT | H2: GST | I2: GST_AMOUNT | J2: PAY_AMOUNT | K2: DATE
A3: 1 | B3: Clothes | C3: Girls Shirts | D3: 70 | E3: =IFERROR(VLOOKUP(C3,'purchase report'!$C$3:$E$12,3,FALSE),"") -> 400 | F3: 600 | G3: =D3*F3 -> 42000 | H3: =IFERROR(VLOOKUP(B3,category!$B$3:$C$7,2,FALSE),"") -> 5 | I3: =F3*H3% -> 30 | J3: =G3+I3 -> 42030 | K3: 46147
A4: 2 | B4: PersonalCare | C4: Shampoo | D4: 150 | E4: =IFERROR(VLOOKUP(C4,'purchase report'!$C$3:$E$12,3,FALSE),"") -> 600 | F4: 800 | G4: =D4*F4 -> 120000 | H4: =IFERROR(VLOOKUP(B4,category!$B$3:$C$7,2,FALSE),"") -> 18 | I4: =F4*H4% -> 144 | J4: =G4+I4 -> 120144 | K4: 46148
A5: 3 | B5: Electronics | C5: TV | D5: 30 | E5: =IFERROR(VLOOKUP(C5,'purchase report'!$C$3:$E$12,3,FALSE),"") -> 32000 | F5: 36000 | G5: =D5*F5 -> 1080000 | H5: =IFERROR(VLOOKUP(B5,category!$B$3:$C$7,2,FALSE),"") -> 12 | I5: =F5*H5% -> 4320 | J5: =G5+I5 -> 1084320 | K5: 46149
A6: 4 | B6: Kitchen | C6: Cooker | D6: 65 | E6: =IFERROR(VLOOKUP(C6,'purchase report'!$C$3:$E$12,3,FALSE),"") -> 1500 | F6: 1800 | G6: =D6*F6 -> 117000 | H6: =IFERROR(VLOOKUP(B6,category!$B$3:$C$7,2,FALSE),"") -> 12 | I6: =F6*H6% -> 216 | J6: =G6+I6 -> 117216 | K6: 46150
A7: 5 | B7: Clothes | C7: T-shirts | D7: 290 | E7: =IFERROR(VLOOKUP(C7,'purchase report'!$C$3:$E$12,3,FALSE),"") -> 700 | F7: 1200 | G7: =D7*F7 -> 348000 | H7: =IFERROR(VLOOKUP(B7,category!$B$3:$C$7,2,FALSE),"") -> 5 | I7: =F7*H7% -> 60 | J7: =G7+I7 -> 348060 | K7: 46151
A8: 6 | B8: PersonalCare | C8: Sunscreen | D8: 100 | E8: =IFERROR(VLOOKUP(C8,'purchase report'!$C$3:$E$12,3,FALSE),"") -> 200 | F8: 350 | G8: =D8*F8 -> 35000 | H8: =IFERROR(VLOOKUP(B8,category!$B$3:$C$7,2,FALSE),"") -> 18 | I8: =F8*H8% -> 63 | J8: =G8+I8 -> 35063 | K8: 46152
A9: 7 | B9: Furniture | C9: Sofa | D9: 15 | E9: =IFERROR(VLOOKUP(C9,'purchase report'!$C$3:$E$12,3,FALSE),"") -> 35000 | F9: 42000 | G9: =D9*F9 -> 630000 | H9: =IFERROR(VLOOKUP(B9,category!$B$3:$C$7,2,FALSE),"") -> 28 | I9: =F9*H9% -> 11760 | J9: =G9+I9 -> 641760 | K9: 46153
A10: 8 | B10: Kitchen | C10: Mixer | D10: 51 | E10: =IFERROR(VLOOKUP(C10,'purchase report'!$C$3:$E$12,3,FALSE),"") -> 2000 | F10: 2400 | G10: =D10*F10 -> 122400 | H10: =IFERROR(VLOOKUP(B10,category!$B$3:$C$7,2,FALSE),"") -> 12 | I10: =F10*H10% -> 288 | J10: =G10+I10 -> 122688 | K10: 46154
A11: 9 | B11: Furniture | C11: Bed | D11: 4 | E11: =IFERROR(VLOOKUP(C11,'purchase report'!$C$3:$E$12,3,FALSE),"") -> 75000 | F11: 85000 | G11: =D11*F11 -> 340000 | H11: =IFERROR(VLOOKUP(B11,category!$B$3:$C$7,2,FALSE),"") -> 28 | I11: =F11*H11% -> 23800 | J11: =G11+I11 -> 363800 | K11: 46155
A12: 10 | B12: Electronics | C12: AC | D12: 34 | E12: =IFERROR(VLOOKUP(C12,'purchase report'!$C$3:$E$12,3,FALSE),"") -> 25000 | F12: 32000 | G12: =D12*F12 -> 1088000 | H12: =IFERROR(VLOOKUP(B12,category!$B$3:$C$7,2,FALSE),"") -> 12 | I12: =F12*H12% -> 3840 | J12: =G12+I12 -> 1091840 | K12: 46156

Sheet stock report
A1: STOCK REPORT
A2: No. | B2: CATEGORY | C2: ITEM_NAME | D2: STOCK | E2: PROFIT
A3: 1 | B3: Clothes | C3: Girls Shirts | D3: =SUMIF('purchase report'!C3:C12,C3,'purchase report'!D3:D12)-SUMIF('sales report'!C3:C12,C3,'sales report'!D3:D12) -> 30 | E3: =('sales report'!F3-'purchase report'!E3)*'sales report'!D3 -> 14000
A4: 2 | B4: PersonalCare | C4: Shampoo | D4: =SUMIF('purchase report'!C4:C13,C4,'purchase report'!D4:D13)-SUMIF('sales report'!C4:C13,C4,'sales report'!D4:D13) -> 50 | E4: =('sales report'!F4-'purchase report'!E4)*'sales report'!D4 -> 30000
A5: 3 | B5: Electronics | C5: TV | D5: =SUMIF('purchase report'!C5:C14,C5,'purchase report'!D5:D14)-SUMIF('sales report'!C5:C14,C5,'sales report'!D5:D14) -> 20 | E5: =('sales report'!F5-'purchase report'!E5)*'sales report'!D5 -> 120000
A6: 4 | B6: Kitchen | C6: Cooker | D6: =SUMIF('purchase report'!C6:C15,C6,'purchase report'!D6:D15)-SUMIF('sales report'!C6:C15,C6,'sales report'!D6:D15) -> 5 | E6: =('sales report'!F6-'purchase report'!E6)*'sales report'!D6 -> 19500
A7: 5 | B7: Clothes | C7: T-shirts | D7: =SUMIF('purchase report'!C7:C16,C7,'purchase report'!D7:D16)-SUMIF('sales report'!C7:C16,C7,'sales report'!D7:D16) -> 10 | E7: =('sales report'!F7-'purchase report'!E7)*'sales report'!D7 -> 145000
A8: 6 | B8: PersonalCare | C8: Sunscreen | D8: =SUMIF('purchase report'!C8:C17,C8,'purchase report'!D8:D17)-SUMIF('sales report'!C8:C17,C8,'sales report'!D8:D17) -> 150 | E8: =('sales report'!F8-'purchase report'!E8)*'sales report'!D8 -> 15000
A9: 7 | B9: Furniture | C9: Sofa | D9: =SUMIF('purchase report'!C9:C18,C9,'purchase report'!D9:D18)-SUMIF('sales report'!C9:C18,C9,'sales report'!D9:D18) -> 5 | E9: =('sales report'!F9-'purchase report'!E9)*'sales report'!D9 -> 105000
A10: 8 | B10: Kitchen | C10: Mixer | D10: =SUMIF('purchase report'!C10:C19,C10,'purchase report'!D10:D19)-SUMIF('sales report'!C10:C19,C10,'sales report'!D10:D19) -> 9 | E10: =('sales report'!F10-'purchase report'!E10)*'sales report'!D10 -> 20400
A11: 9 | B11: Furniture | C11: Bed | D11: =SUMIF('purchase report'!C11:C20,C11,'purchase report'!D11:D20)-SUMIF('sales report'!C11:C20,C11,'sales report'!D11:D20) -> 6 | E11: =('sales report'!F11-'purchase report'!E11)*'sales report'!D11 -> 40000
A12: 10 | B12: Electronics | C12: AC | D12: =SUMIF('purchase report'!C12:C21,C12,'purchase report'!D12:D21)-SUMIF('sales report'!C12:C21,C12,'sales report'!D12:D21) -> 11 | E12: =('sales report'!F12-'purchase report'!E12)*'sales report'!D12 -> 238000

Sheet subcategory
A1: No. | B1: CATEGORY | C1: ITEM_NAME
A2: 1 | B2: Clothes | C2: Girls Shirts
A3: 2 | B3: Clothes | C3: T-shirts
A4: 3 | B4: PersonalCare | C4: Shampoo
A5: 4 | B5: PersonalCare | C5: Sunscreen
A6: 5 | B6: Electronics | C6: TV
A7: 6 | B7: Electronics | C7: AC
A8: 7 | B8: Kitchen | C8: Cooker
A9: 8 | B9: Kitchen | C9: Mixer
A10: 9 | B10: Furniture | C10: Sofa
A11: 10 | B11: Furniture | C11: Bed
